omniview/__init__.py
omniview/managers.py
omniview/threads.py
omniview-1.2.0.dist-info/licenses/LICENSE
omniview-1.2.0.dist-info/METADATA
omniview-1.2.0.dist-info/WHEEL
omniview-1.2.0.dist-info/top_level.txt
omniview-1.2.0.dist-info/RECORD
