Metadata-Version: 2.4
Name: omniview
Version: 1.2.0
Summary: Receiving video stream from multiple cameras (usb/ip) for further processing
Author-email: DIMFLIX <dimflix.official@gmail.com>
Maintainer-email: DIMFLIX <dimflix.official@gmail.com>
License-Expression: GPL-3.0-or-later
Project-URL: Homepage, https://github.com/DIMFLIX/OmniView
Project-URL: Documentation, https://github.com/DIMFLIX/OmniView/wiki
Project-URL: Repository, https://github.com/DIMFLIX/OmniView.git
Project-URL: Bug Tracker, https://github.com/DIMFLIX/OmniView/issues
Project-URL: Changelog, https://github.com/DIMFLIX/OmniView/blob/master/CHANGELOG.md
Keywords: python,opencv,iot,ai,surveillance,tensorflow,raspberrypi,realtime,multithreading,pytorch,yolo,machinelearning,deeplearning,computervision,objectdetection,neuralnetworks,videostreaming,videoprocessing,multicamera
Classifier: Intended Audience :: Developers
Classifier: Intended Audience :: Science/Research
Classifier: Topic :: Scientific/Engineering :: Artificial Intelligence
Classifier: Topic :: Scientific/Engineering :: Image Processing
Classifier: Topic :: Software Development :: Libraries :: Python Modules
Classifier: Topic :: Multimedia :: Video
Classifier: Programming Language :: Python :: 3
Classifier: Programming Language :: Python :: 3.8
Classifier: Programming Language :: Python :: 3.9
Classifier: Programming Language :: Python :: 3.10
Classifier: Programming Language :: Python :: 3.11
Classifier: Programming Language :: Python :: 3.12
Classifier: Operating System :: OS Independent
Requires-Python: >=3.8
License-File: LICENSE
Requires-Dist: opencv-python>=4.11.0.86
Dynamic: license-file
